{
  "sina_sectors": [
    {
      "名称": "元件",
      "涨跌幅": 3.01,
      "总成交额": 707.43,
      "净流入": 39.63,
      "成交额": 707.43
    },
    {
      "名称": "其他电子",
      "涨跌幅": 2.48,
      "总成交额": 182.08,
      "净流入": 14.49,
      "成交额": 182.08
    },
    {
      "名称": "半导体",
      "涨跌幅": 2.37,
      "总成交额": 1808.26,
      "净流入": 64.64,
      "成交额": 1808.26
    },
    {
      "名称": "互联网电商",
      "涨跌幅": 2.35,
      "总成交额": 39.99,
      "净流入": 2.87,
      "成交额": 39.99
    },
    {
      "名称": "港口航运",
      "涨跌幅": 2.32,
      "总成交额": 185.26,
      "净流入": 18.68,
      "成交额": 185.26
    },
    {
      "名称": "种植业与林业",
      "涨跌幅": 2.2,
      "总成交额": 161.28,
      "净流入": 3.83,
      "成交额": 161.28
    },
    {
      "名称": "白酒",
      "涨跌幅": 1.79,
      "总成交额": 175.22,
      "净流入": 14.3,
      "成交额": 175.22
    },
    {
      "名称": "通信服务",
      "涨跌幅": 1.43,
      "总成交额": 271.06,
      "净流入": -2.13,
      "成交额": 271.06
    },
    {
      "名称": "文化传媒",
      "涨跌幅": 1.41,
      "总成交额": 213.35,
      "净流入": 12.49,
      "成交额": 213.35
    },
    {
      "名称": "食品加工制造",
      "涨跌幅": 1.32,
      "总成交额": 83.18,
      "净流入": 5.05,
      "成交额": 83.18
    },
    {
      "名称": "养殖业",
      "涨跌幅": 1.25,
      "总成交额": 100.27,
      "净流入": 2.23,
      "成交额": 100.27
    },
    {
      "名称": "影视院线",
      "涨跌幅": 1.22,
      "总成交额": 45.78,
      "净流入": 3.78,
      "成交额": 45.78
    },
    {
      "名称": "化学纤维",
      "涨跌幅": 1.1,
      "总成交额": 154.43,
      "净流入": -4.95,
      "成交额": 154.43
    },
    {
      "名称": "旅游及酒店",
      "涨跌幅": 0.98,
      "总成交额": 46.88,
      "净流入": 0.99,
      "成交额": 46.88
    },
    {
      "名称": "教育",
      "涨跌幅": 0.9,
      "总成交额": 15.46,
      "净流入": -0.22,
      "成交额": 15.46
    },
    {
      "名称": "消费电子",
      "涨跌幅": 0.86,
      "总成交额": 498.0,
      "净流入": 9.76,
      "成交额": 498.0
    },
    {
      "名称": "多元金融",
      "涨跌幅": 0.81,
      "总成交额": 122.56,
      "净流入": -18.3,
      "成交额": 122.56
    },
    {
      "名称": "计算机设备",
      "涨跌幅": 0.81,
      "总成交额": 236.34,
      "净流入": -5.47,
      "成交额": 236.34
    },
    {
      "名称": "零售",
      "涨跌幅": 0.78,
      "总成交额": 132.25,
      "净流入": 6.13,
      "成交额": 132.25
    },
    {
      "名称": "电子化学品",
      "涨跌幅": 0.77,
      "总成交额": 254.88,
      "净流入": 2.35,
      "成交额": 254.88
    },
    {
      "名称": "房地产",
      "涨跌幅": 0.74,
      "总成交额": 152.25,
      "净流入": 0.2,
      "成交额": 152.25
    },
    {
      "名称": "军工电子",
      "涨跌幅": 0.67,
      "总成交额": 297.23,
      "净流入": -3.1,
      "成交额": 297.23
    },
    {
      "名称": "软件开发",
      "涨跌幅": 0.65,
      "总成交额": 456.61,
      "净流入": -0.11,
      "成交额": 456.61
    },
    {
      "名称": "饮料制造",
      "涨跌幅": 0.65,
      "总成交额": 56.57,
      "净流入": 2.19,
      "成交额": 56.57
    },
    {
      "名称": "汽车整车",
      "涨跌幅": 0.6,
      "总成交额": 212.78,
      "净流入": 33.35,
      "成交额": 212.78
    },
    {
      "名称": "化学制药",
      "涨跌幅": 0.6,
      "总成交额": 276.2,
      "净流入": -4.9,
      "成交额": 276.2
    },
    {
      "名称": "美容护理",
      "涨跌幅": 0.57,
      "总成交额": 34.69,
      "净流入": 0.07,
      "成交额": 34.69
    },
    {
      "名称": "银行",
      "涨跌幅": 0.45,
      "总成交额": 249.38,
      "净流入": 3.34,
      "成交额": 249.38
    },
    {
      "名称": "IT服务",
      "涨跌幅": 0.44,
      "总成交额": 532.17,
      "净流入": -11.1,
      "成交额": 532.17
    },
    {
      "名称": "生物制品",
      "涨跌幅": 0.44,
      "总成交额": 82.88,
      "净流入": -1.09,
      "成交额": 82.88
    },
    {
      "名称": "包装印刷",
      "涨跌幅": 0.42,
      "总成交额": 107.14,
      "净流入": -0.47,
      "成交额": 107.14
    },
    {
      "名称": "中药",
      "涨跌幅": 0.4,
      "总成交额": 74.12,
      "净流入": 0.19,
      "成交额": 74.12
    },
    {
      "名称": "黑色家电",
      "涨跌幅": 0.39,
      "总成交额": 47.93,
      "净流入": -2.61,
      "成交额": 47.93
    },
    {
      "名称": "电池",
      "涨跌幅": 0.39,
      "总成交额": 881.93,
      "净流入": -6.23,
      "成交额": 881.93
    },
    {
      "名称": "塑料制品",
      "涨跌幅": 0.38,
      "总成交额": 204.36,
      "净流入": 2.11,
      "成交额": 204.36
    },
    {
      "名称": "光学光电子",
      "涨跌幅": 0.34,
      "总成交额": 458.25,
      "净流入": -32.81,
      "成交额": 458.25
    },
    {
      "名称": "医疗服务",
      "涨跌幅": 0.31,
      "总成交额": 184.5,
      "净流入": -5.78,
      "成交额": 184.5
    },
    {
      "名称": "环保设备",
      "涨跌幅": 0.3,
      "总成交额": 51.17,
      "净流入": -1.49,
      "成交额": 51.17
    },
    {
      "名称": "综合",
      "涨跌幅": 0.29,
      "总成交额": 131.36,
      "净流入": -9.18,
      "成交额": 131.36
    },
    {
      "名称": "汽车服务及其他",
      "涨跌幅": 0.29,
      "总成交额": 24.85,
      "净流入": 1.07,
      "成交额": 24.85
    },
    {
      "名称": "物流",
      "涨跌幅": 0.27,
      "总成交额": 72.84,
      "净流入": -1.19,
      "成交额": 72.84
    },
    {
      "名称": "军工装备",
      "涨跌幅": 0.26,
      "总成交额": 492.2,
      "净流入": -17.54,
      "成交额": 492.2
    },
    {
      "名称": "白色家电",
      "涨跌幅": 0.26,
      "总成交额": 124.71,
      "净流入": -0.38,
      "成交额": 124.71
    },
    {
      "名称": "其他社会服务",
      "涨跌幅": 0.26,
      "总成交额": 56.65,
      "净流入": 1.14,
      "成交额": 56.65
    },
    {
      "名称": "医疗器械",
      "涨跌幅": 0.14,
      "总成交额": 211.88,
      "净流入": -4.21,
      "成交额": 211.88
    },
    {
      "名称": "家居用品",
      "涨跌幅": 0.12,
      "总成交额": 94.95,
      "净流入": -1.37,
      "成交额": 94.95
    },
    {
      "名称": "专用设备",
      "涨跌幅": 0.08,
      "总成交额": 487.2,
      "净流入": 6.35,
      "成交额": 487.2
    },
    {
      "名称": "通用设备",
      "涨跌幅": 0.04,
      "总成交额": 666.67,
      "净流入": -22.57,
      "成交额": 666.67
    },
    {
      "名称": "公路铁路运输",
      "涨跌幅": 0.01,
      "总成交额": 46.68,
      "净流入": 1.5,
      "成交额": 46.68
    },
    {
      "名称": "医药商业",
      "涨跌幅": -0.02,
      "总成交额": 37.16,
      "净流入": -0.65,
      "成交额": 37.16
    },
    {
      "名称": "橡胶制品",
      "涨跌幅": -0.04,
      "总成交额": 46.13,
      "净流入": -0.65,
      "成交额": 46.13
    },
    {
      "名称": "自动化设备",
      "涨跌幅": -0.05,
      "总成交额": 403.62,
      "净流入": -3.89,
      "成交额": 403.62
    },
    {
      "名称": "油气开采及服务",
      "涨跌幅": -0.08,
      "总成交额": 234.84,
      "净流入": -6.05,
      "成交额": 234.84
    },
    {
      "名称": "造纸",
      "涨跌幅": -0.1,
      "总成交额": 43.82,
      "净流入": 0.62,
      "成交额": 43.82
    },
    {
      "名称": "贸易",
      "涨跌幅": -0.1,
      "总成交额": 25.89,
      "净流入": 0.42,
      "成交额": 25.89
    },
    {
      "名称": "电机",
      "涨跌幅": -0.12,
      "总成交额": 50.12,
      "净流入": -3.55,
      "成交额": 50.12
    },
    {
      "名称": "农产品加工",
      "涨跌幅": -0.14,
      "总成交额": 94.7,
      "净流入": -1.87,
      "成交额": 94.7
    },
    {
      "名称": "汽车零部件",
      "涨跌幅": -0.15,
      "总成交额": 506.99,
      "净流入": -17.2,
      "成交额": 506.99
    },
    {
      "名称": "纺织制造",
      "涨跌幅": -0.17,
      "总成交额": 32.32,
      "净流入": -0.9,
      "成交额": 32.32
    },
    {
      "名称": "化学制品",
      "涨跌幅": -0.18,
      "总成交额": 562.58,
      "净流入": -27.3,
      "成交额": 562.58
    },
    {
      "名称": "保险",
      "涨跌幅": -0.21,
      "总成交额": 85.05,
      "净流入": 3.24,
      "成交额": 85.05
    },
    {
      "名称": "小家电",
      "涨跌幅": -0.29,
      "总成交额": 26.03,
      "净流入": -0.24,
      "成交额": 26.03
    },
    {
      "名称": "服装家纺",
      "涨跌幅": -0.3,
      "总成交额": 74.24,
      "净流入": -2.5,
      "成交额": 74.24
    },
    {
      "名称": "建筑材料",
      "涨跌幅": -0.3,
      "总成交额": 212.0,
      "净流入": -9.49,
      "成交额": 212.0
    },
    {
      "名称": "游戏",
      "涨跌幅": -0.33,
      "总成交额": 115.35,
      "净流入": -6.95,
      "成交额": 115.35
    },
    {
      "名称": "证券",
      "涨跌幅": -0.33,
      "总成交额": 214.48,
      "净流入": -13.92,
      "成交额": 214.48
    },
    {
      "名称": "建筑装饰",
      "涨跌幅": -0.35,
      "总成交额": 686.21,
      "净流入": -73.7,
      "成交额": 686.21
    },
    {
      "名称": "通信设备",
      "涨跌幅": -0.38,
      "总成交额": 1176.58,
      "净流入": 38.61,
      "成交额": 1176.58
    },
    {
      "名称": "环境治理",
      "涨跌幅": -0.42,
      "总成交额": 209.85,
      "净流入": -11.29,
      "成交额": 209.85
    },
    {
      "名称": "轨交设备",
      "涨跌幅": -0.45,
      "总成交额": 35.64,
      "净流入": -3.57,
      "成交额": 35.64
    },
    {
      "名称": "机场航运",
      "涨跌幅": -0.48,
      "总成交额": 55.93,
      "净流入": -8.18,
      "成交额": 55.93
    },
    {
      "名称": "其他电源设备",
      "涨跌幅": -0.61,
      "总成交额": 242.86,
      "净流入": -13.18,
      "成交额": 242.86
    },
    {
      "名称": "厨卫电器",
      "涨跌幅": -0.73,
      "总成交额": 22.02,
      "净流入": -2.25,
      "成交额": 22.02
    },
    {
      "名称": "石油加工贸易",
      "涨跌幅": -0.76,
      "总成交额": 139.59,
      "净流入": -9.58,
      "成交额": 139.59
    },
    {
      "名称": "燃气",
      "涨跌幅": -0.8,
      "总成交额": 50.5,
      "净流入": -4.92,
      "成交额": 50.5
    },
    {
      "名称": "风电设备",
      "涨跌幅": -0.88,
      "总成交额": 467.63,
      "净流入": -15.99,
      "成交额": 467.63
    },
    {
      "名称": "电网设备",
      "涨跌幅": -1.06,
      "总成交额": 682.67,
      "净流入": -29.59,
      "成交额": 682.67
    },
    {
      "名称": "非金属材料",
      "涨跌幅": -1.07,
      "总成交额": 47.71,
      "净流入": -0.14,
      "成交额": 47.71
    },
    {
      "名称": "金属新材料",
      "涨跌幅": -1.08,
      "总成交额": 87.14,
      "净流入": -7.77,
      "成交额": 87.14
    },
    {
      "名称": "光伏设备",
      "涨跌幅": -1.16,
      "总成交额": 644.99,
      "净流入": -42.99,
      "成交额": 644.99
    },
    {
      "名称": "工程机械",
      "涨跌幅": -1.3,
      "总成交额": 93.31,
      "净流入": -9.07,
      "成交额": 93.31
    },
    {
      "名称": "化学原料",
      "涨跌幅": -1.66,
      "总成交额": 420.15,
      "净流入": -27.33,
      "成交额": 420.15
    },
    {
      "名称": "小金属",
      "涨跌幅": -1.81,
      "总成交额": 421.27,
      "净流入": -23.69,
      "成交额": 421.27
    },
    {
      "名称": "工业金属",
      "涨跌幅": -1.85,
      "总成交额": 729.47,
      "净流入": -56.6,
      "成交额": 729.47
    },
    {
      "名称": "能源金属",
      "涨跌幅": -2.12,
      "总成交额": 169.94,
      "净流入": -10.75,
      "成交额": 169.94
    },
    {
      "名称": "农化制品",
      "涨跌幅": -2.19,
      "总成交额": 560.62,
      "净流入": -55.47,
      "成交额": 560.62
    },
    {
      "名称": "电力",
      "涨跌幅": -2.2,
      "总成交额": 827.72,
      "净流入": -80.38,
      "成交额": 827.72
    },
    {
      "名称": "煤炭开采加工",
      "涨跌幅": -2.59,
      "总成交额": 215.56,
      "净流入": -15.58,
      "成交额": 215.56
    },
    {
      "名称": "钢铁",
      "涨跌幅": -3.6,
      "总成交额": 231.8,
      "净流入": -36.34,
      "成交额": 231.8
    },
    {
      "名称": "贵金属",
      "涨跌幅": -3.74,
      "总成交额": 210.48,
      "净流入": -10.24,
      "成交额": 210.48
    }
  ],
  "ths_sectors": [
    {
      "名称": "元件",
      "涨跌幅": 3.01,
      "总成交额": 707.43,
      "净流入": 39.63
    },
    {
      "名称": "其他电子",
      "涨跌幅": 2.48,
      "总成交额": 182.08,
      "净流入": 14.49
    },
    {
      "名称": "半导体",
      "涨跌幅": 2.37,
      "总成交额": 1808.26,
      "净流入": 64.64
    },
    {
      "名称": "互联网电商",
      "涨跌幅": 2.35,
      "总成交额": 39.99,
      "净流入": 2.87
    },
    {
      "名称": "港口航运",
      "涨跌幅": 2.32,
      "总成交额": 185.26,
      "净流入": 18.68
    },
    {
      "名称": "种植业与林业",
      "涨跌幅": 2.2,
      "总成交额": 161.28,
      "净流入": 3.83
    },
    {
      "名称": "白酒",
      "涨跌幅": 1.79,
      "总成交额": 175.22,
      "净流入": 14.3
    },
    {
      "名称": "通信服务",
      "涨跌幅": 1.43,
      "总成交额": 271.06,
      "净流入": -2.13
    },
    {
      "名称": "文化传媒",
      "涨跌幅": 1.41,
      "总成交额": 213.35,
      "净流入": 12.49
    },
    {
      "名称": "食品加工制造",
      "涨跌幅": 1.32,
      "总成交额": 83.18,
      "净流入": 5.05
    },
    {
      "名称": "养殖业",
      "涨跌幅": 1.25,
      "总成交额": 100.27,
      "净流入": 2.23
    },
    {
      "名称": "影视院线",
      "涨跌幅": 1.22,
      "总成交额": 45.78,
      "净流入": 3.78
    },
    {
      "名称": "化学纤维",
      "涨跌幅": 1.1,
      "总成交额": 154.43,
      "净流入": -4.95
    },
    {
      "名称": "旅游及酒店",
      "涨跌幅": 0.98,
      "总成交额": 46.88,
      "净流入": 0.99
    },
    {
      "名称": "教育",
      "涨跌幅": 0.9,
      "总成交额": 15.46,
      "净流入": -0.22
    },
    {
      "名称": "消费电子",
      "涨跌幅": 0.86,
      "总成交额": 498.0,
      "净流入": 9.76
    },
    {
      "名称": "多元金融",
      "涨跌幅": 0.81,
      "总成交额": 122.56,
      "净流入": -18.3
    },
    {
      "名称": "计算机设备",
      "涨跌幅": 0.81,
      "总成交额": 236.34,
      "净流入": -5.47
    },
    {
      "名称": "零售",
      "涨跌幅": 0.78,
      "总成交额": 132.25,
      "净流入": 6.13
    },
    {
      "名称": "电子化学品",
      "涨跌幅": 0.77,
      "总成交额": 254.88,
      "净流入": 2.35
    },
    {
      "名称": "房地产",
      "涨跌幅": 0.74,
      "总成交额": 152.25,
      "净流入": 0.2
    },
    {
      "名称": "军工电子",
      "涨跌幅": 0.67,
      "总成交额": 297.23,
      "净流入": -3.1
    },
    {
      "名称": "软件开发",
      "涨跌幅": 0.65,
      "总成交额": 456.61,
      "净流入": -0.11
    },
    {
      "名称": "饮料制造",
      "涨跌幅": 0.65,
      "总成交额": 56.57,
      "净流入": 2.19
    },
    {
      "名称": "汽车整车",
      "涨跌幅": 0.6,
      "总成交额": 212.78,
      "净流入": 33.35
    },
    {
      "名称": "化学制药",
      "涨跌幅": 0.6,
      "总成交额": 276.2,
      "净流入": -4.9
    },
    {
      "名称": "美容护理",
      "涨跌幅": 0.57,
      "总成交额": 34.69,
      "净流入": 0.07
    },
    {
      "名称": "银行",
      "涨跌幅": 0.45,
      "总成交额": 249.38,
      "净流入": 3.34
    },
    {
      "名称": "IT服务",
      "涨跌幅": 0.44,
      "总成交额": 532.17,
      "净流入": -11.1
    },
    {
      "名称": "生物制品",
      "涨跌幅": 0.44,
      "总成交额": 82.88,
      "净流入": -1.09
    },
    {
      "名称": "包装印刷",
      "涨跌幅": 0.42,
      "总成交额": 107.14,
      "净流入": -0.47
    },
    {
      "名称": "中药",
      "涨跌幅": 0.4,
      "总成交额": 74.12,
      "净流入": 0.19
    },
    {
      "名称": "黑色家电",
      "涨跌幅": 0.39,
      "总成交额": 47.93,
      "净流入": -2.61
    },
    {
      "名称": "电池",
      "涨跌幅": 0.39,
      "总成交额": 881.93,
      "净流入": -6.23
    },
    {
      "名称": "塑料制品",
      "涨跌幅": 0.38,
      "总成交额": 204.36,
      "净流入": 2.11
    },
    {
      "名称": "光学光电子",
      "涨跌幅": 0.34,
      "总成交额": 458.25,
      "净流入": -32.81
    },
    {
      "名称": "医疗服务",
      "涨跌幅": 0.31,
      "总成交额": 184.5,
      "净流入": -5.78
    },
    {
      "名称": "环保设备",
      "涨跌幅": 0.3,
      "总成交额": 51.17,
      "净流入": -1.49
    },
    {
      "名称": "综合",
      "涨跌幅": 0.29,
      "总成交额": 131.36,
      "净流入": -9.18
    },
    {
      "名称": "汽车服务及其他",
      "涨跌幅": 0.29,
      "总成交额": 24.85,
      "净流入": 1.07
    },
    {
      "名称": "物流",
      "涨跌幅": 0.27,
      "总成交额": 72.84,
      "净流入": -1.19
    },
    {
      "名称": "军工装备",
      "涨跌幅": 0.26,
      "总成交额": 492.2,
      "净流入": -17.54
    },
    {
      "名称": "白色家电",
      "涨跌幅": 0.26,
      "总成交额": 124.71,
      "净流入": -0.38
    },
    {
      "名称": "其他社会服务",
      "涨跌幅": 0.26,
      "总成交额": 56.65,
      "净流入": 1.14
    },
    {
      "名称": "医疗器械",
      "涨跌幅": 0.14,
      "总成交额": 211.88,
      "净流入": -4.21
    },
    {
      "名称": "家居用品",
      "涨跌幅": 0.12,
      "总成交额": 94.95,
      "净流入": -1.37
    },
    {
      "名称": "专用设备",
      "涨跌幅": 0.08,
      "总成交额": 487.2,
      "净流入": 6.35
    },
    {
      "名称": "通用设备",
      "涨跌幅": 0.04,
      "总成交额": 666.67,
      "净流入": -22.57
    },
    {
      "名称": "公路铁路运输",
      "涨跌幅": 0.01,
      "总成交额": 46.68,
      "净流入": 1.5
    },
    {
      "名称": "医药商业",
      "涨跌幅": -0.02,
      "总成交额": 37.16,
      "净流入": -0.65
    },
    {
      "名称": "橡胶制品",
      "涨跌幅": -0.04,
      "总成交额": 46.13,
      "净流入": -0.65
    },
    {
      "名称": "自动化设备",
      "涨跌幅": -0.05,
      "总成交额": 403.62,
      "净流入": -3.89
    },
    {
      "名称": "油气开采及服务",
      "涨跌幅": -0.08,
      "总成交额": 234.84,
      "净流入": -6.05
    },
    {
      "名称": "造纸",
      "涨跌幅": -0.1,
      "总成交额": 43.82,
      "净流入": 0.62
    },
    {
      "名称": "贸易",
      "涨跌幅": -0.1,
      "总成交额": 25.89,
      "净流入": 0.42
    },
    {
      "名称": "电机",
      "涨跌幅": -0.12,
      "总成交额": 50.12,
      "净流入": -3.55
    },
    {
      "名称": "农产品加工",
      "涨跌幅": -0.14,
      "总成交额": 94.7,
      "净流入": -1.87
    },
    {
      "名称": "汽车零部件",
      "涨跌幅": -0.15,
      "总成交额": 506.99,
      "净流入": -17.2
    },
    {
      "名称": "纺织制造",
      "涨跌幅": -0.17,
      "总成交额": 32.32,
      "净流入": -0.9
    },
    {
      "名称": "化学制品",
      "涨跌幅": -0.18,
      "总成交额": 562.58,
      "净流入": -27.3
    },
    {
      "名称": "保险",
      "涨跌幅": -0.21,
      "总成交额": 85.05,
      "净流入": 3.24
    },
    {
      "名称": "小家电",
      "涨跌幅": -0.29,
      "总成交额": 26.03,
      "净流入": -0.24
    },
    {
      "名称": "服装家纺",
      "涨跌幅": -0.3,
      "总成交额": 74.24,
      "净流入": -2.5
    },
    {
      "名称": "建筑材料",
      "涨跌幅": -0.3,
      "总成交额": 212.0,
      "净流入": -9.49
    },
    {
      "名称": "游戏",
      "涨跌幅": -0.33,
      "总成交额": 115.35,
      "净流入": -6.95
    },
    {
      "名称": "证券",
      "涨跌幅": -0.33,
      "总成交额": 214.48,
      "净流入": -13.92
    },
    {
      "名称": "建筑装饰",
      "涨跌幅": -0.35,
      "总成交额": 686.21,
      "净流入": -73.7
    },
    {
      "名称": "通信设备",
      "涨跌幅": -0.38,
      "总成交额": 1176.58,
      "净流入": 38.61
    },
    {
      "名称": "环境治理",
      "涨跌幅": -0.42,
      "总成交额": 209.85,
      "净流入": -11.29
    },
    {
      "名称": "轨交设备",
      "涨跌幅": -0.45,
      "总成交额": 35.64,
      "净流入": -3.57
    },
    {
      "名称": "机场航运",
      "涨跌幅": -0.48,
      "总成交额": 55.93,
      "净流入": -8.18
    },
    {
      "名称": "其他电源设备",
      "涨跌幅": -0.61,
      "总成交额": 242.86,
      "净流入": -13.18
    },
    {
      "名称": "厨卫电器",
      "涨跌幅": -0.73,
      "总成交额": 22.02,
      "净流入": -2.25
    },
    {
      "名称": "石油加工贸易",
      "涨跌幅": -0.76,
      "总成交额": 139.59,
      "净流入": -9.58
    },
    {
      "名称": "燃气",
      "涨跌幅": -0.8,
      "总成交额": 50.5,
      "净流入": -4.92
    },
    {
      "名称": "风电设备",
      "涨跌幅": -0.88,
      "总成交额": 467.63,
      "净流入": -15.99
    },
    {
      "名称": "电网设备",
      "涨跌幅": -1.06,
      "总成交额": 682.67,
      "净流入": -29.59
    },
    {
      "名称": "非金属材料",
      "涨跌幅": -1.07,
      "总成交额": 47.71,
      "净流入": -0.14
    },
    {
      "名称": "金属新材料",
      "涨跌幅": -1.08,
      "总成交额": 87.14,
      "净流入": -7.77
    },
    {
      "名称": "光伏设备",
      "涨跌幅": -1.16,
      "总成交额": 644.99,
      "净流入": -42.99
    },
    {
      "名称": "工程机械",
      "涨跌幅": -1.3,
      "总成交额": 93.31,
      "净流入": -9.07
    },
    {
      "名称": "化学原料",
      "涨跌幅": -1.66,
      "总成交额": 420.15,
      "净流入": -27.33
    },
    {
      "名称": "小金属",
      "涨跌幅": -1.81,
      "总成交额": 421.27,
      "净流入": -23.69
    },
    {
      "名称": "工业金属",
      "涨跌幅": -1.85,
      "总成交额": 729.47,
      "净流入": -56.6
    },
    {
      "名称": "能源金属",
      "涨跌幅": -2.12,
      "总成交额": 169.94,
      "净流入": -10.75
    },
    {
      "名称": "农化制品",
      "涨跌幅": -2.19,
      "总成交额": 560.62,
      "净流入": -55.47
    },
    {
      "名称": "电力",
      "涨跌幅": -2.2,
      "总成交额": 827.72,
      "净流入": -80.38
    },
    {
      "名称": "煤炭开采加工",
      "涨跌幅": -2.59,
      "总成交额": 215.56,
      "净流入": -15.58
    },
    {
      "名称": "钢铁",
      "涨跌幅": -3.6,
      "总成交额": 231.8,
      "净流入": -36.34
    },
    {
      "名称": "贵金属",
      "涨跌幅": -3.74,
      "总成交额": 210.48,
      "净流入": -10.24
    }
  ],
  "market": {
    "change_pct": -0.26,
    "amount": 1037223833963.0,
    "price": 4084.7858,
    "name": "上证指数",
    "update_time": "15:35:24"
  },
  "update_time": "15:35:24"
}